speterlin_stocks/__init__.py
speterlin_stocks/module1.py
speterlin_stocks-1.3.0.dist-info/licenses/LICENSE
speterlin_stocks-1.3.0.dist-info/METADATA
speterlin_stocks-1.3.0.dist-info/WHEEL
speterlin_stocks-1.3.0.dist-info/top_level.txt
speterlin_stocks-1.3.0.dist-info/RECORD
