Metadata-Version: 2.4
Name: speterlin-stocks
Version: 1.3.0
Summary: A Python package for a suite of quant-trading opportunities in stocks with API integration: Alpaca brokerage for storing USD assets and margin trading (2x) on exchanges NYSE & NASDAQ, Financial Modeling Prep (FMP) & Google Trends & Yahoo Finance & Google Finance & ExchangeRate & Slickcharts & CrunchBase for data collection, OpenAI & Google Gemini-Pro for AI analysis.
Author-email: Sebastian Peterlin <speterlin@smartxchange.xyz>
License: MIT
Project-URL: Homepage, https://github.com/speterlin/speterlin-stocks
Requires-Python: >=3.12
License-File: LICENSE
Requires-Dist: requests>=2.20
Requires-Dist: numpy
Requires-Dist: pandas>=2.0
Requires-Dist: datetime
Requires-Dist: yfinance==0.1.52
Requires-Dist: beautifulsoup4
Requires-Dist: pytrends
Requires-Dist: fake-headers
Requires-Dist: unidecode
Requires-Dist: pytz
Requires-Dist: alpaca-trade-api
Requires-Dist: openai
Requires-Dist: langchain-openai
Requires-Dist: google-generativeai
Requires-Dist: twilio
Dynamic: license-file
